mlllearnzebra/__init__.py
mlllearnzebra/core.py
mlllearnzebra-0.1.0.dist-info/METADATA
mlllearnzebra-0.1.0.dist-info/WHEEL
mlllearnzebra-0.1.0.dist-info/top_level.txt
mlllearnzebra-0.1.0.dist-info/RECORD
