Metadata-Version: 2.4
Name: mlllearnzebra
Version: 0.1.0
Summary: View machine learning algorithms as code
Home-page: https://github.com/Mahi044/mlllearnzebra
Author: Balayya
Author-email: 
Classifier: Programming Language :: Python :: 3
Classifier: Operating System :: OS Independent
Classifier: License :: OSI Approved :: MIT License
Requires-Python: >=3.7
Dynamic: author
Dynamic: classifier
Dynamic: description
Dynamic: description-content-type
Dynamic: home-page
Dynamic: requires-python
Dynamic: summary
